threaded_buffered_pipeline.py
threaded_buffered_pipeline-0.0.8.dist-info/LICENSE
threaded_buffered_pipeline-0.0.8.dist-info/METADATA
threaded_buffered_pipeline-0.0.8.dist-info/WHEEL
threaded_buffered_pipeline-0.0.8.dist-info/top_level.txt
threaded_buffered_pipeline-0.0.8.dist-info/RECORD
